MANIFEST.in
README.md
setup.py
linkInventory/__init__.py
linkInventory/app_run.py
linkInventory.egg-info/PKG-INFO
linkInventory.egg-info/SOURCES.txt
linkInventory.egg-info/dependency_links.txt
linkInventory.egg-info/entry_points.txt
linkInventory.egg-info/not-zip-safe
linkInventory.egg-info/requires.txt
linkInventory.egg-info/top_level.txt
linkInventory/configs/__init__.py
linkInventory/configs/config_cli.py
linkInventory/configs/config_handler.py
linkInventory/db/__init__.py
linkInventory/db/db_api.py
linkInventory/db/engine.py
linkInventory/db/models.py
linkInventory/restapi/__init__.py
linkInventory/restapi/routes.py
linkInventory/tests/__init__.py