Metadata-Version: 1.0
Name: linkInventory
Version: 1.2
Summary: WAN link inventory management 
Home-page: https://github.com/microservice-tsp-billing/linkInventory
Author: Bhujay Kumar Bhatta
Author-email: bhujay.bhatta@yahoo.com
License: Apache Software License
Platform: UNKNOWN
